agt/__init__.py
agt/__main__.py
agt/cli.py
agt/vscode.py
agt/worktree.py
agent_tools_drnt-0.4.3.dist-info/METADATA
agent_tools_drnt-0.4.3.dist-info/WHEEL
agent_tools_drnt-0.4.3.dist-info/entry_points.txt
agent_tools_drnt-0.4.3.dist-info/RECORD
