Metadata-Version: 2.4
Name: agent-tools-drnt
Version: 0.4.3
Summary: Worktree-based agent workflow management toolkit
Author: Agent Tools Contributors
License: MIT
Requires-Python: >=3.11
Requires-Dist: colorama>=0.4.6
Provides-Extra: cli
Requires-Dist: colorama>=0.4.6; extra == 'cli'
Provides-Extra: dev
Requires-Dist: pytest-cov>=4.0.0; extra == 'dev'
Requires-Dist: pytest-xdist>=3.0.0; extra == 'dev'
Requires-Dist: pytest>=7.0.0; extra == 'dev'
Requires-Dist: ruff>=0.1.0; extra == 'dev'
